vedro_pairwise/__init__.py
vedro_pairwise/py.typed
vedro_pairwise-0.1.0.dist-info/LICENSE
vedro_pairwise-0.1.0.dist-info/METADATA
vedro_pairwise-0.1.0.dist-info/WHEEL
vedro_pairwise-0.1.0.dist-info/RECORD
