Metadata-Version: 2.1
Name: vedro-pairwise
Version: 0.1.0
Summary: Optimize test coverage by generating minimal test cases through pairwise parameter combinations
Home-page: https://github.com/mickeystreicher/vedro-pairwise
License: Apache-2.0
Author: Mickey Streicher
Author-email: mickeystreicher@fastmail.us
Requires-Python: >=3.8
Classifier: License :: OSI Approved :: Apache Software License
Classifier: Programming Language :: Python :: 3
Classifier: Programming Language :: Python :: 3.8
Classifier: Programming Language :: Python :: 3.9
Classifier: Programming Language :: Python :: 3.10
Classifier: Programming Language :: Python :: 3.11
Classifier: Programming Language :: Python :: 3.12
Classifier: Programming Language :: Python :: 3.13
Classifier: Typing :: Typed
Requires-Dist: allpairspy (>=2.0,<3.0)
Requires-Dist: vedro (>=1.9,<2.0)
Project-URL: Repository, https://github.com/mickeystreicher/vedro-pairwise
